{
    "order": "1016",
    "filename": "IMAGE_1016.jpg",
    "url": "https://lh5.googleusercontent.com/p/AF1QipOhFq8OgtO9bks016mqMZ6qGHy-LM_XQ2JEvHlG=w1920-h1080-k-no",
    "factory": "BANDO DESIGN LIMITED",
    "city": "Dhaka",
    "category": "BANGLADESH",
    "address": "Purba Narsinghapur, Earpur Union Parishad Road, Ashulia",
    "truelat": "23.9331661",
    "truelng": "90.3052096",
    "lat": "-195.3334",
    "lng": "181.3708",
    "tag": "Piles; ",
    "tags": [
        "BANGLADESH"
    ]
}