{
    "order": "3410",
    "filename": "IMAGE_3410.jpg",
    "url": "https://lh5.googleusercontent.com/p/AF1QipM1uMUonafFmYKc_ZUF0cUG3wnpz2wVjaTRSSbk=w1920-h1080-k-no",
    "factory": "KAROONI FASHIONS LTD",
    "city": "Gazipur",
    "category": "BANGLADESH",
    "address": "Ratanpur, Shafipur, Kaliakoir",
    "clusters": "Logos; ",
    "truelat": "24.0552221",
    "truelng": "90.2867581",
    "lat": "-213.2788",
    "lng": "-213.3275",
    "tag": "Logos; ",
    "tags": [
        "BANGLADESH"
    ]
}