{
    "order": "986",
    "filename": "IMAGE_0986.jpg",
    "url": "https://lh5.googleusercontent.com/p/AF1QipOXZrjZcdn9IovsfgJOVqmap-kXU2qZdmEvTA8=w1920-h1080-k-no",
    "factory": "AZGARD9 LIMITED",
    "city": "Lahore",
    "category": "PAKISTAN",
    "address": "2.5 Km Off Manga, Raiwind Road, District Kasur",
    "clusters": "Celebrations; People outside; ",
    "truelat": "31.2633166",
    "truelng": "74.1388542",
    "lat": "16.5246",
    "lng": "-70.3853",
    "tag": "Celebrations; People outside; ",
    "tags": [
        "PAKISTAN"
    ]
}