{
    "order": "3026",
    "filename": "IMAGE_3026.jpg",
    "url": "https://lh5.googleusercontent.com/p/AF1QipOibDYC6XMaxj58llYfdcmEN84fowvwutdPfQcR=w1920-h1080-k-no",
    "factory": "FASHION COM LIMTED",
    "city": "Dhaka",
    "category": "BANGLADESH",
    "address": "Durgapur Ashulia Savar",
    "clusters": "Woman; Safety; ",
    "truelat": "23.8991129",
    "truelng": "90.3253311",
    "lat": "-78.5757",
    "lng": "12.2062",
    "tag": "Woman; Safety; ",
    "tags": [
        "BANGLADESH"
    ]
}