{
    "order": "3854",
    "filename": "IMAGE_3854.jpg",
    "url": "https://lh5.googleusercontent.com/p/AF1QipPwGTiB4ZiBEjQm3BdQVQr2zyqIA0U06DFt9hMf=w1920-h1080-k-no",
    "factory": "MIYA KONFEKSIYON DOKUMA TEKSTIL SAN. VE TIC. A.S.",
    "city": "Bursa",
    "category": "TURKEY",
    "address": "Demirtas Organize San. Bolgesi Cigdem 1 Sok. No: 23",
    "clusters": "",
    "truelat": "40.257035",
    "truelng": "29.078575",
    "lat": "0",
    "lng": "0",
    "tag": "",
    "tags": [
        "TURKEY"
    ]
}