{
    "order": "353",
    "filename": "IMAGE_0353.jpg",
    "url": "https://lh5.googleusercontent.com/p/AF1QipN6WKYDTVvMLafVQiq39MOOlM2-HjtxM_6MqzTC=w1920-h1080-k-no",
    "factory": "FAKIR APPARELS",
    "city": "Dhaka",
    "category": "BANGLADESH",
    "address": "Mouza-Baroivhog, Bscic Industrial Area, Enayetnagar, Fatullah Narayanganj",
    "clusters": "Celebrations; ",
    "truelat": "23.6422928",
    "truelng": "90.4816582",
    "lat": "22.7687",
    "lng": "-9.5456",
    "tag": "Celebrations; ",
    "tags": [
        "BANGLADESH"
    ]
}