{
    "order": "1143",
    "filename": "IMAGE_1143.jpg",
    "url": "https://lh5.googleusercontent.com/p/AF1QipOhpJ67IpniEz2mX9rx--SAcdRsBMIehfvxgSM4=w1920-h1080-k-no",
    "factory": "BIRDS A & Z LTD",
    "city": "Dhaka",
    "category": "BANGLADESH",
    "address": "Plot-113, Baipail, Ashulia",
    "clusters": "People outside; Selfie; ",
    "truelat": "23.9325782",
    "truelng": "90.2784385",
    "lat": "-18.6105",
    "lng": "-101.0057",
    "tag": "People outside; Selfie; ",
    "tags": [
        "BANGLADESH"
    ]
}