{
    "order": "3056",
    "filename": "IMAGE_3056.jpg",
    "url": "https://lh5.googleusercontent.com/p/AF1QipOV_JCvtBB8xTHJnqf2hvpJV2Cr_86eqIibTvh6=w1920-h1080-k-no",
    "factory": "GARMENTS EXPORT VILLAGE LTD",
    "city": "Gazipur",
    "category": "BANGLADESH",
    "address": "Kbm Road, Tongi Industrial Area, Tongi",
    "clusters": "Office; ",
    "truelat": "23.8983775",
    "truelng": "90.4036268",
    "lat": "-271.4278",
    "lng": "-38.4394",
    "tag": "Office; ",
    "tags": [
        "BANGLADESH"
    ]
}