{
    "order": "4046",
    "filename": "IMAGE_4046.jpg",
    "url": "https://lh5.googleusercontent.com/p/AF1QipM6SUXF3FVU_x6r3pW-_mrpkovCL-ZQnUQMkiBv=w1920-h1080-k-no",
    "factory": "MUAZUDDIN TEXTILE LTD",
    "city": "Dhaka",
    "category": "BANGLADESH",
    "address": "235/236 East Chandura Shafipur Kaliakoir Gazipur",
    "clusters": "Machines; ",
    "truelat": "24.069452",
    "truelng": "90.222418",
    "lat": "-37.6313",
    "lng": "199.0125",
    "tag": "Machines; ",
    "tags": [
        "BANGLADESH"
    ]
}