{
    "order": "3213",
    "filename": "IMAGE_3213.jpg",
    "url": "https://lh5.googleusercontent.com/p/AF1QipP3DMN8L9HGrgf0j8dW6wQjZiJz-B5ccpk-Lj1g=w1920-h1080-k-no",
    "factory": "YEN MY EXPORT GARMENT",
    "city": "Hung Yen",
    "category": "VIETNAM",
    "address": "Giai Pham Village, Giai Pham Ward, Yen My District",
    "truelat": "20.935692",
    "truelng": "106.0258126",
    "lat": "-144.6633",
    "lng": "-253.038",
    "tag": "Vehicles; Logos; ",
    "tags": [
        "VIETNAM"
    ]
}