{
    "order": "1093",
    "filename": "IMAGE_1093.jpg",
    "url": "https://lh5.googleusercontent.com/p/AF1QipMzWZQY84TRb5cxRjNrS5QfnHw8DWI1kpujb1jp=w1920-h1080-k-no",
    "factory": "BANDO DESIGN LIMITED",
    "city": "Dhaka",
    "category": "BANGLADESH",
    "address": "Purba Narsinghapur, Earpur Union Parishad Road, Ashulia",
    "clusters": "Woman; Machines; Piles; ",
    "truelat": "23.9331661",
    "truelng": "90.3052096",
    "lat": "-104.3795",
    "lng": "123.5902",
    "tag": "Woman; Machines; Piles; ",
    "tags": [
        "BANGLADESH"
    ]
}