{
    "order": "5646",
    "filename": "IMAGE_5646.jpg",
    "url": "https://lh5.googleusercontent.com/p/AF1QipPhAOH5a483201xAgCaRCzV0N4VWhnNHIA9eZMF=w1920-h1080-k-no",
    "factory": "ZABER & ZUBAIR FABRICS LTD",
    "city": "Dhaka",
    "category": "BANGLADESH",
    "address": "Pagar, Munno Nagar, Tongi",
    "clusters": "People outside; Vehicles; ",
    "truelat": "23.9028244",
    "truelng": "90.4040473",
    "lat": "-87.344",
    "lng": "-304.3165",
    "tag": "People outside; Vehicles; ",
    "tags": [
        "BANGLADESH"
    ]
}