{
    "order": "109",
    "filename": "IMAGE_0109.jpg",
    "url": "https://lh5.googleusercontent.com/p/AF1QipOBFn31c1NphJt_4zvIux8_nScIxwuewuhT4riY=w1920-h1080-k-no",
    "factory": "AKAR TEKSTIL",
    "city": "Izmir",
    "category": "TURKEY",
    "address": "10003 Sk No:3, 35620 Aosb/\u00c7i\u011fli",
    "clusters": "Office; ",
    "truelat": "38.4819006",
    "truelng": "27.0475492",
    "lat": "-282.3454",
    "lng": "-71.0179",
    "tag": "Office; ",
    "tags": [
        "TURKEY"
    ]
}