{
    "order": "2885",
    "filename": "IMAGE_2885.jpg",
    "url": "https://lh5.googleusercontent.com/p/AF1QipN5ZaY9pnU0aPSK41tIJ-US8_od7AoeSZhW6Lpx=w1920-h1080-k-no",
    "factory": "FASHION COM LIMTED",
    "city": "Dhaka",
    "category": "BANGLADESH",
    "address": "Durgapur Ashulia Savar",
    "clusters": "Woman; Signs; Piles; ",
    "truelat": "23.8991129",
    "truelng": "90.3253311",
    "lat": "-125.9334",
    "lng": "68.3933",
    "tag": "Woman; Signs; Piles; ",
    "tags": [
        "BANGLADESH"
    ]
}