{
    "order": "4854",
    "filename": "IMAGE_4854.jpg",
    "url": "https://lh5.googleusercontent.com/wmkg8E7ktdFXHB87MkvNRqJrs6gc8qObDzRNNXHabA8TGHvh2ZG7wbTB9qXlWV5hnA=w1920-h1080-k-no",
    "factory": "SHENGJIE (MYANMAR ) CLTOHING CO.,LTD",
    "city": "Yangon",
    "category": "MYANMAR",
    "address": "Plot No.296/297 Sayar Shan Street, Shwe Linnpan Industrial Zone, Hlaingtharyar Township, Yangon, 11181",
    "veralat": "16.8470857",
    "veralng": "96.0752172",
    "lat": "-205.3188",
    "lng": "-248.8845",
    "tag": "Logos; Signs; ",
    "tags": [
        "MYANMAR"
    ]
}