{
    "order": "3134",
    "filename": "IMAGE_3134.jpg",
    "url": "https://lh5.googleusercontent.com/p/AF1QipN70B8qF8vbiTVp1Rc8d0kSLXie02pWEeQAnX0m=w1920-h1080-k-no",
    "factory": "GUL AHMED TEXTILE MILLS LIMITED",
    "city": "Karachi",
    "category": "PAKISTAN",
    "address": "Plot # Ht-7 Landhi Industrial Area , 75136",
    "veralat": "24.8461562",
    "veralng": "67.2341377",
    "lat": "-44.4102",
    "lng": "5.7496",
    "tag": "Snack; Signs; ",
    "tags": [
        "PAKISTAN"
    ]
}