{
    "order": "6260",
    "filename": "IMAGE_6260.jpg",
    "url": "https://lh5.googleusercontent.com/p/AF1QipPRZPpJzt5TEdPYA3aOgHembVLKf8ISsJp6e476=w1920-h1080-k-no",
    "factory": "ODESSA FASHIONS LIMITED",
    "city": "Gazipur",
    "category": "BANGLADESH",
    "address": "Nalzani, Chandana, Joydevpur, Gazipur, 1711",
    "veralat": "23.9912898",
    "veralng": "90.3805646",
    "lat": "-187.2508",
    "lng": "83.6574",
    "tag": "Signs; Piles; ",
    "tags": [
        "BANGLADESH"
    ]
}