{
    "order": "2204",
    "filename": "IMAGE_2204.jpg",
    "url": "https://lh5.googleusercontent.com/p/AF1QipNQpVO1QqMrMkSXDPfQGg_LuM1Cd5Kt9p19W-6q=w1920-h1080-k-no",
    "factory": "DIRD COMPOSITE TEXTILES LIMITED",
    "city": "Gazipur",
    "category": "BANGLADESH",
    "address": "Shathiabari, Dhaladia, Rajendrapur, Sreepur,, Rajendrapur, Sreepur,Gazipur-1741 1751",
    "veralat": "24.1996574",
    "veralng": "90.4809098",
    "lat": "0",
    "lng": "0",
    "tag": "",
    "tags": [
        "BANGLADESH"
    ]
}