{
    "order": "466",
    "filename": "IMAGE_466.jpg",
    "url": "https://lh5.googleusercontent.com/p/AF1QipPTDGNLWK_38in9XhNv3CymkxRYeKsHcS2eTI1C=w1920-h1080-k-no",
    "factory": "MATRIX SWEATERS LIMITED",
    "city": "Gazipur",
    "category": "BANGLADESH",
    "address": "Choydana, National University, Gazipur., 1704",
    "veralat": "23.9504063",
    "veralng": "90.380132",
    "lat": "24.684",
    "lng": "-146.2694",
    "tag": "People outside; ",
    "tags": [
        "BANGLADESH"
    ]
}