{
    "order": "961",
    "filename": "IMAGE_961.jpg",
    "url": "https://lh5.googleusercontent.com/p/AF1QipOuZVAHO1_QNyKpUDIX29dI0kiuH3RPilrKQnd3=w1920-h1080-k-no",
    "factory": "AYESHA CLOTHING CO. LIMITED",
    "city": "Dhaka",
    "category": "BANGLADESH",
    "address": "Bangobondhu Road, Tongabari, Ashulia, Savar, Dhaka, 1341",
    "veralat": "23.896017",
    "veralng": "90.3229675",
    "lat": "-21.3988",
    "lng": "177.6899",
    "tag": "Machines; ",
    "tags": [
        "BANGLADESH"
    ]
}