{
    "order": "1066",
    "filename": "IMAGE_1066.jpg",
    "url": "https://lh5.googleusercontent.com/p/AF1QipOptKKGt_fZtK-F6k-Ikr0L7sC6qMSuiq2QyA4q=w1920-h1080-k-no",
    "factory": "BANDO DESIGN LIMITED",
    "city": "Dhaka",
    "category": "BANGLADESH",
    "address": "Purba Narsinghapur, Earpur Union Parishad Road, Ashulia, Dhaka-1341, 1341",
    "veralat": "23.9331661",
    "veralng": "90.3052096",
    "lat": "12.0801",
    "lng": "-167.4205",
    "tag": "People outside; ",
    "tags": [
        "BANGLADESH"
    ]
}