{
    "order": "29",
    "filename": "IMAGE_29.jpg",
    "url": "https://lh5.googleusercontent.com/p/AF1QipNBamadio4BES_aP_Xa_18u37cNbnl_nHqY_keu=w1920-h1080-k-no",
    "factory": "SCARLET KNITWEARS",
    "city": "Fatullah",
    "category": "BANGLADESH",
    "address": "Plot B# 160-163, Bscic I/E, Fatullah, Narayangonj, Bangladesh",
    "veralat": "23.6241907",
    "veralng": "90.4797296",
    "lat": "-141.2332",
    "lng": "-8.8846",
    "tag": "Signs; Safety; ",
    "tags": [
        "BANGLADESH"
    ]
}