{
    "order": "6347",
    "filename": "IMAGE_6347.jpg",
    "url": "https://lh5.googleusercontent.com/p/AF1QipPxxpQJryRHN4iBCPLfm13aN_e23oXujG7aMCSD=w1920-h1080-k-no",
    "factory": "ODESSA FASHIONS LIMITED",
    "city": "Gazipur",
    "category": "BANGLADESH",
    "address": "Nalzani, Chandana, Joydevpur, Gazipur, 1798",
    "veralat": "23.9912898",
    "veralng": "90.3805646",
    "lat": "-30.2611",
    "lng": "110.8541",
    "tag": "Woman; Machines; ",
    "tags": [
        "BANGLADESH"
    ]
}