{
    "order": "4656",
    "filename": "IMAGE_4656.jpg",
    "url": "https://lh5.googleusercontent.com/p/AF1QipMKNkvHjHdU2HxTj7kZV9rq8OBXLbio7pynEQQu=w1920-h1080-k-no",
    "factory": "SAAD MUSA FABRICS LIMITED. UNIT-3",
    "city": "Chittagong",
    "category": "BANGLADESH",
    "address": "Khaja Road, Kulgaon, Jalalabad, Chittagong., 4214",
    "veralat": "22.4038074",
    "veralng": "91.8254921",
    "lat": "-47.0052",
    "lng": "210.7499",
    "tag": "Machines; ",
    "tags": [
        "BANGLADESH"
    ]
}