{
    "order": "2070",
    "filename": "IMAGE_2070.jpg",
    "url": "https://lh5.googleusercontent.com/p/AF1QipNa24HNLfKeT4ziU5eqf1rWyTNHN66FXBIz6U8U=w1920-h1080-k-no",
    "factory": "ARTISTIC FABRIC & GARMENT UNIT K-13",
    "city": "Karachi",
    "category": "PAKISTAN",
    "address": "Plot No. 6 & 7 , Sec # 21 Korangi Industrial Area",
    "veralat": "24.8387414",
    "veralng": "67.1209226",
    "lat": "-52.6277",
    "lng": "-284.1079",
    "tag": "Vehicles; ",
    "tags": [
        "PAKISTAN"
    ]
}